antonnia/__init__.py
antonnia/events/__init__.py
antonnia/events/py.typed
antonnia/events/types/__init__.py
antonnia/events/types/app_connection_created.py
antonnia/events/types/event.py
antonnia/events/types/event_base.py
antonnia/events/types/message_created.py
antonnia/events/types/session_created.py
antonnia/events/types/session_finished.py
antonnia/events/types/session_transferred.py
antonnia_events-1.0.8.dist-info/licenses/LICENSE
antonnia_events-1.0.8.dist-info/METADATA
antonnia_events-1.0.8.dist-info/WHEEL
antonnia_events-1.0.8.dist-info/top_level.txt
antonnia_events-1.0.8.dist-info/RECORD
