Metadata-Version: 2.4
Name: antonnia-events
Version: 1.0.8
Summary: Python SDK for Antonnia Events and Webhooks
Home-page: https://github.com/antonnia/antonnia-python
Author: Antonnia
Author-email: Antonnia <support@antonnia.com>
Maintainer-email: Antonnia <support@antonnia.com>
License: MIT
Project-URL: Homepage, https://antonnia.com
Project-URL: Documentation, https://docs.antonnia.com/events
Project-URL: Repository, https://github.com/antonnia/antonnia-python
Project-URL: Bug Tracker, https://github.com/antonnia/antonnia-python/issues
Keywords: antonnia,events,webhooks,api,sdk
Classifier: Development Status :: 5 - Production/Stable
Classifier: Intended Audience :: Developers
Classifier: License :: OSI Approved :: MIT License
Classifier: Operating System :: OS Independent
Classifier: Programming Language :: Python :: 3
Classifier: Programming Language :: Python :: 3.8
Classifier: Programming Language :: Python :: 3.9
Classifier: Programming Language :: Python :: 3.10
Classifier: Programming Language :: Python :: 3.11
Classifier: Programming Language :: Python :: 3.12
Classifier: Topic :: Communications :: Chat
Classifier: Topic :: Software Development :: Libraries :: Python Modules
Classifier: Topic :: Internet :: WWW/HTTP :: Dynamic Content
Classifier: Topic :: Software Development :: Libraries :: Python Modules
Classifier: Typing :: Typed
Requires-Python: >=3.8
License-File: LICENSE
Requires-Dist: pydantic<3.0.0,>=2.7.0
Requires-Dist: typing-extensions>=4.0.0; python_version < "3.10"
Requires-Dist: antonnia-conversations>=2.0.3
Requires-Dist: antonnia-apps>=1.0.1
Provides-Extra: dev
Requires-Dist: pytest>=7.0.0; extra == "dev"
Requires-Dist: pytest-asyncio>=0.21.0; extra == "dev"
Requires-Dist: black>=23.0.0; extra == "dev"
Requires-Dist: mypy>=1.0.0; extra == "dev"
Requires-Dist: isort>=5.12.0; extra == "dev"
Requires-Dist: flake8>=6.0.0; extra == "dev"
Dynamic: author
Dynamic: home-page
Dynamic: license-file
Dynamic: requires-python
